setup.py
easywebassets/__init__.py
easywebassets/asset_types.py
easywebassets/assets.py
easywebassets/package.py
easywebassets.egg-info/PKG-INFO
easywebassets.egg-info/SOURCES.txt
easywebassets.egg-info/dependency_links.txt
easywebassets.egg-info/not-zip-safe
easywebassets.egg-info/requires.txt
easywebassets.egg-info/top_level.txt