Metadata-Version: 1.0
Name: easywebassets
Version: 0.1
Summary: An easier way to use webassets
Home-page: http://github.com/frascoweb/easywebassets
Author: Maxime Bouroumeau-Fuseau
Author-email: maxime.bouroumeau@gmail.com
License: MIT
Platform: any
